aki/__init__.py
aki/app.py
aki/chainlit.md
aki/chainlit_zh-CN.md
aki/console_print.py
aki/event_handler.py
aki/init_aki.py
aki/version.py
aki/.chainlit/config.toml
aki/.chainlit/translations/bn.json
aki/.chainlit/translations/en-US.json
aki/.chainlit/translations/gu.json
aki/.chainlit/translations/he-IL.json
aki/.chainlit/translations/hi.json
aki/.chainlit/translations/ja.json
aki/.chainlit/translations/kn.json
aki/.chainlit/translations/ml.json
aki/.chainlit/translations/mr.json
aki/.chainlit/translations/nl-NL.json
aki/.chainlit/translations/nl.json
aki/.chainlit/translations/ta.json
aki/.chainlit/translations/te.json
aki/.chainlit/translations/zh-CN.json
aki/callback/__init__.py
aki/callback/chainlit_callback.py
aki/callback/usage_callback.py
aki/chat/export_conversation.py
aki/chat/profile_factory.py
aki/chat/profile_registry.py
aki/chat/base/agent_profile.py
aki/chat/base/base_profile.py
aki/chat/base/environment_details.py
aki/chat/graph/agent_graph.py
aki/chat/graph/supervisor_graph.py
aki/chat/implementations/agent/__init__.py
aki/chat/implementations/supervisor/aki_team.py
aki/config/.env.example
aki/config/__init__.py
aki/config/constants.py
aki/config/environment.py
aki/config/logging.yaml
aki/config/logging_config.py
aki/config/mcp_settings.default.json
aki/config/mcp_settings.template.json
aki/config/paths.py
aki/config/profile_manager.py
aki/llm/__init__.py
aki/llm/capabilities.py
aki/llm/factory.py
aki/llm/reasoning.py
aki/llm/token_counter.py
aki/llm/providers/__init__.py
aki/llm/providers/base.py
aki/llm/providers/bedrock.py
aki/llm/providers/ollama.py
aki/persistence/__init__.py
aki/persistence/chainlit_sqlite_adapter.py
aki/persistence/dal.py
aki/persistence/database_factory.py
aki/persistence/database_manager.py
aki/persistence/database_schema.sql
aki/persistence/database_schema_sqlite.sql
aki/persistence/local_file_storage.py
aki/persistence/models.py
aki/persistence/postgres_manager.py
aki/persistence/sqlite_manager.py
aki/profiles/aki.json
aki_ai-2025.4.30.dist-info/METADATA
aki_ai-2025.4.30.dist-info/WHEEL
aki_ai-2025.4.30.dist-info/entry_points.txt
aki_ai-2025.4.30.dist-info/licenses/LICENSE
aki_ai-2025.4.30.dist-info/RECORD
