Metadata-Version: 2.4
Name: aki-ai
Version: 2025.4.30
Summary: Aki - An advanced AI assistant framework
Project-URL: Documentation, https://github.com/Aki-community/aki#readme
Project-URL: Issues, https://github.com/Aki-community/aki/issues
Project-URL: Source, https://github.com/Aki-community/aki
License-Expression: MIT
License-File: LICENSE
Requires-Python: >=3.12
Requires-Dist: aiosqlite>=0.19.0
Requires-Dist: asyncpg>=0.25
Requires-Dist: chainlit==2.5.5
Requires-Dist: chardet>=5.2.0
Requires-Dist: colorama==0.4.6
Requires-Dist: duckduckgo-search<=8.0.0
Requires-Dist: jsonschema>=4.23.0
Requires-Dist: langchain-aws>=0.2.19
Requires-Dist: langchain-community==0.3.22
Requires-Dist: langchain-ollama>=0.3.1
Requires-Dist: langchain==0.3.24
Requires-Dist: langgraph==0.3.34
Requires-Dist: markitdown[all]>=0.1.1
Requires-Dist: mcp>=1.6.0
Requires-Dist: ollama>=0.4.7
Requires-Dist: onnxruntime==1.19.2
Requires-Dist: pathspec==0.12.1
Requires-Dist: psutil==5.9.8
Requires-Dist: pydantic>=2.10.6
Requires-Dist: python-dotenv>=1.1.0
Requires-Dist: sqlalchemy[asyncio]>=2.0.0
Requires-Dist: sqlparse>=0.5.3
Requires-Dist: tiktoken>=0.8.0
Requires-Dist: tiktoken>=0.9.0
Requires-Dist: tree-sitter-c-sharp>=0.23.0
Requires-Dist: tree-sitter-c>=0.23.0
Requires-Dist: tree-sitter-cpp>=0.23.0
Requires-Dist: tree-sitter-css>=0.23.0
Requires-Dist: tree-sitter-go>=0.23.0
Requires-Dist: tree-sitter-java>=0.23.0
Requires-Dist: tree-sitter-javascript>=0.23.0
Requires-Dist: tree-sitter-php>=0.23.0
Requires-Dist: tree-sitter-python>=0.23.0
Requires-Dist: tree-sitter-ruby>=0.23.0
Requires-Dist: tree-sitter-rust>=0.23.0
Requires-Dist: tree-sitter-scala>=0.23.0
Requires-Dist: tree-sitter-typescript>=0.23.0
Requires-Dist: tree-sitter==0.24.0
Requires-Dist: wcmatch==10.0
Provides-Extra: dev
Requires-Dist: coverage>=7.8.0; extra == 'dev'
Requires-Dist: flake8>=6.1.0; extra == 'dev'
Requires-Dist: hatch>=1.14.1; extra == 'dev'
Requires-Dist: pip>=25.0.1; extra == 'dev'
Requires-Dist: pytest-asyncio>=0.26.0; extra == 'dev'
Requires-Dist: pytest-cov>=4.1.0; extra == 'dev'
Requires-Dist: pytest>=7.4.0; extra == 'dev'
Requires-Dist: ruff>=0.11.4; extra == 'dev'
